InstructorEmbedding/__init__.py
InstructorEmbedding/instructor.py
InstructorEmbedding-1.0.1.dist-info/LICENSE
InstructorEmbedding-1.0.1.dist-info/METADATA
InstructorEmbedding-1.0.1.dist-info/WHEEL
InstructorEmbedding-1.0.1.dist-info/top_level.txt
InstructorEmbedding-1.0.1.dist-info/RECORD
