Metadata-Version: 2.1
Name: InstructorEmbedding
Version: 1.0.1
Summary: Text embedding tool
Home-page: https://github.com/HKUNLP/instructor-embedding
Author: Hongjin SU
Author-email: hjsu@cs.hku.hk
License: Apache License 2.0
Keywords: sentence,embedding,text,nlp,instructor
Platform: UNKNOWN
